{
  "toolkit": "0.7.1",
  "timestamp": "2025-02-09T19:00:49.381303",
  "trackers": {
    "DMTrack": {
      "command": "rgbd",
      "label": "DMTrack",
      "protocol": "traxpython",
      "arguments": {},
      "env": {},
      "paths": "/data/2024/DMTrack/lib/test/vot"
    }
  },
  "sequences": {
    "backpack_indoor": {
      "length": 2111,
      "width": 640,
      "height": 360
    },
    "bag01_indoor": {
      "length": 2463,
      "width": 640,
      "height": 360
    },
    "bag02_indoor": {
      "length": 2904,
      "width": 640,
      "height": 360
    },
    "ball01_wild": {
      "length": 531,
      "width": 640,
      "height": 360
    },
    "ball06_indoor": {
      "length": 781,
      "width": 640,
      "height": 360
    },
    "ball10_wild": {
      "length": 2089,
      "width": 640,
      "height": 360
    },
    "ball11_wild": {
      "length": 1576,
      "width": 640,
      "height": 360
    },
    "ball15_wild": {
      "length": 179,
      "width": 640,
      "height": 360
    },
    "ball18_indoor": {
      "length": 3699,
      "width": 640,
      "height": 360
    },
    "ball20_indoor": {
      "length": 1691,
      "width": 640,
      "height": 360
    },
    "bandlight_indoor": {
      "length": 1190,
      "width": 640,
      "height": 360
    },
    "beautifullight02_indoor": {
      "length": 975,
      "width": 640,
      "height": 360
    },
    "book03_indoor": {
      "length": 716,
      "width": 640,
      "height": 360
    },
    "bottle04_indoor": {
      "length": 2286,
      "width": 640,
      "height": 360
    },
    "card_indoor": {
      "length": 2416,
      "width": 640,
      "height": 360
    },
    "cat01_indoor": {
      "length": 3035,
      "width": 640,
      "height": 360
    },
    "colacan03_indoor": {
      "length": 2076,
      "width": 640,
      "height": 360
    },
    "cube02_indoor": {
      "length": 3816,
      "width": 640,
      "height": 360
    },
    "cube03_indoor": {
      "length": 610,
      "width": 640,
      "height": 360
    },
    "cube05_indoor": {
      "length": 2975,
      "width": 640,
      "height": 360
    },
    "cup01_indoor": {
      "length": 1361,
      "width": 640,
      "height": 360
    },
    "cup02_indoor": {
      "length": 1758,
      "width": 640,
      "height": 360
    },
    "cup04_indoor": {
      "length": 2235,
      "width": 640,
      "height": 360
    },
    "cup12_indoor": {
      "length": 1006,
      "width": 640,
      "height": 360
    },
    "developmentboard_indoor": {
      "length": 1527,
      "width": 640,
      "height": 360
    },
    "duck03_wild": {
      "length": 492,
      "width": 640,
      "height": 360
    },
    "dumbbells01_indoor": {
      "length": 1056,
      "width": 640,
      "height": 360
    },
    "earphone01_indoor": {
      "length": 1090,
      "width": 640,
      "height": 360
    },
    "file01_indoor": {
      "length": 1628,
      "width": 640,
      "height": 360
    },
    "flag_indoor": {
      "length": 1371,
      "width": 640,
      "height": 360
    },
    "glass01_indoor": {
      "length": 2233,
      "width": 640,
      "height": 360
    },
    "hand01_indoor": {
      "length": 1223,
      "width": 640,
      "height": 360
    },
    "human02_indoor": {
      "length": 1740,
      "width": 640,
      "height": 360
    },
    "lock02_indoor": {
      "length": 521,
      "width": 640,
      "height": 360
    },
    "mobilephone03_indoor": {
      "length": 677,
      "width": 640,
      "height": 360
    },
    "notebook01_indoor": {
      "length": 2000,
      "width": 640,
      "height": 360
    },
    "pigeon01_wild": {
      "length": 668,
      "width": 640,
      "height": 360
    },
    "pigeon02_wild": {
      "length": 303,
      "width": 640,
      "height": 360
    },
    "pigeon04_wild": {
      "length": 143,
      "width": 640,
      "height": 360
    },
    "pot_indoor": {
      "length": 1056,
      "width": 640,
      "height": 360
    },
    "roller_indoor": {
      "length": 850,
      "width": 640,
      "height": 360
    },
    "shoes02_indoor": {
      "length": 1317,
      "width": 640,
      "height": 360
    },
    "squirrel_wild": {
      "length": 1010,
      "width": 640,
      "height": 360
    },
    "stick_indoor": {
      "length": 903,
      "width": 640,
      "height": 360
    },
    "toiletpaper01_indoor": {
      "length": 1600,
      "width": 640,
      "height": 360
    },
    "toy02_indoor": {
      "length": 1140,
      "width": 640,
      "height": 360
    },
    "toy09_indoor": {
      "length": 1344,
      "width": 640,
      "height": 360
    },
    "ukulele01_indoor": {
      "length": 1613,
      "width": 640,
      "height": 360
    },
    "yogurt_indoor": {
      "length": 1614,
      "width": 640,
      "height": 360
    },
    "adapter01_indoor": {
      "length": 2775,
      "width": 640,
      "height": 360
    }
  },
  "results": {
    "rgbd-unsupervised": {
      "parameters": {
        "realtime": null,
        "noise": null,
        "inject": null,
        "transformers": [],
        "analyses": [
          {
            "name": null,
            "resolution": 100,
            "ignore_unknown": true,
            "bounded": true,
            "ignore_masks": "_ignore",
            "beta": 1.0,
            "type": "vot.analysis.longterm.PrecisionRecall"
          },
          {
            "name": null,
            "resolution": 100,
            "ignore_unknown": true,
            "bounded": true,
            "ignore_masks": "_ignore",
            "type": "vot.analysis.longterm.PrecisionRecallCurve"
          },
          {
            "name": null,
            "beta": 1.0,
            "resolution": 100,
            "ignore_unknown": true,
            "bounded": true,
            "ignore_masks": "_ignore",
            "type": "vot.analysis.longterm.FScoreCurve"
          }
        ],
        "ignore_special": true,
        "repetitions": 1,
        "early_stop": true,
        "multiobject": false
      },
      "type": "vot.experiment.multirun.UnsupervisedExperiment",
      "results": [
        [
          [
            0.6468077304265566,
            0.647871294902578,
            0.6473390758113502
          ]
        ],
        [
          [
            [
              [
                0.0,
                1.0
              ],
              [
                0.007416134872954056,
                0.9808452340391114
              ],
              [
                0.017439061988511865,
                0.9249547503152833
              ],
              [
                0.02168152783698152,
                0.891604512953605
              ],
              [
                0.025406879713597945,
                0.8973620887455322
              ],
              [
                0.030072614379756456,
                0.8731788800500659
              ],
              [
                0.03442402022622201,
                0.8647665468036684
              ],
              [
                0.03951623639803014,
                0.842572508761249
              ],
              [
                0.04441919953202285,
                0.8182660047687277
              ],
              [
                0.04999251143685924,
                0.8185682841660373
              ],
              [
                0.05573139725650929,
                0.8120908494542275
              ],
              [
                0.06188764774266857,
                0.8017252456829889
              ],
              [
                0.06889769075685657,
                0.8052542826761814
              ],
              [
                0.0759415358663908,
                0.8020802390579739
              ],
              [
                0.0829239771968071,
                0.7961847923024062
              ],
              [
                0.09018920513155487,
                0.7966528296106096
              ],
              [
                0.0980480670034325,
                0.7889754682080675
              ],
              [
                0.10553205471529084,
                0.7852132711906151
              ],
              [
                0.11327063818294394,
                0.7856032024695793
              ],
              [
                0.12042224291168555,
                0.7815162214179106
              ],
              [
                0.12808756762717277,
                0.7782642981654504
              ],
              [
                0.13597686071653897,
                0.7746883386624502
              ],
              [
                0.14299707081919125,
                0.772869954256965
              ],
              [
                0.1506459694399949,
                0.7694733834786354
              ],
              [
                0.15857780639023392,
                0.7678719785218071
              ],
              [
                0.16622212959917954,
                0.7682544536262048
              ],
              [
                0.17377079756783168,
                0.766887142799207
              ],
              [
                0.18174851964588343,
                0.7655234306809819
              ],
              [
                0.1896463071125222,
                0.7580961013563698
              ],
              [
                0.19803662069560427,
                0.7566547413693143
              ],
              [
                0.20656712548730805,
                0.7514799045617899
              ],
              [
                0.21434193667709295,
                0.7484905501225176
              ],
              [
                0.22219778414944422,
                0.7457498435557721
              ],
              [
                0.22994730658286358,
                0.740515959272038
              ],
              [
                0.23777792476036372,
                0.7362705078313367
              ],
              [
                0.24595884595224266,
                0.7315916001939974
              ],
              [
                0.2541566550425294,
                0.7284702263596401
              ],
              [
                0.262212795061721,
                0.7259234880965466
              ],
              [
                0.2700905955188779,
                0.7246774780075304
              ],
              [
                0.27793661773575684,
                0.7216336192403903
              ],
              [
                0.28570089401370885,
                0.7191520666190288
              ],
              [
                0.2934505810136565,
                0.7167145591447226
              ],
              [
                0.3013377006868759,
                0.7157108283898351
              ],
              [
                0.30967126589732763,
                0.7139600092494166
              ],
              [
                0.31722628382268203,
                0.7130226117632631
              ],
              [
                0.32495543546544936,
                0.7119585915374362
              ],
              [
                0.33297138647189967,
                0.7111805672571755
              ],
              [
                0.3401518776200567,
                0.709528595947163
              ],
              [
                0.3476680908218265,
                0.7079124078790793
              ],
              [
                0.35470654510576827,
                0.7069063007899092
              ],
              [
                0.3619938151021471,
                0.7063830609353758
              ],
              [
                0.36933229225010694,
                0.7052941645859431
              ],
              [
                0.3770056647741237,
                0.7046700591572054
              ],
              [
                0.38426622714518954,
                0.7036718562345095
              ],
              [
                0.3919003021419062,
                0.702571599624173
              ],
              [
                0.39893665549298474,
                0.7019601088953469
              ],
              [
                0.4064625428435676,
                0.7011564436796541
              ],
              [
                0.4131521910089662,
                0.6998977196858935
              ],
              [
                0.4200104735446925,
                0.6981997407592787
              ],
              [
                0.42712702093362737,
                0.6965536163783688
              ],
              [
                0.4340718745576108,
                0.6953117615694933
              ],
              [
                0.4420571905419224,
                0.6946713527999056
              ],
              [
                0.44908026190221934,
                0.6935140735390108
              ],
              [
                0.4560972998003875,
                0.693170776179738
              ],
              [
                0.4631733533111865,
                0.6926794006882495
              ],
              [
                0.47021040298400124,
                0.6916079089301383
              ],
              [
                0.47686617621969696,
                0.6905518494830669
              ],
              [
                0.4837499133949183,
                0.6899480868926193
              ],
              [
                0.49065577552369194,
                0.6887913921783664
              ],
              [
                0.4971422468615297,
                0.687405275330063
              ],
              [
                0.5036162106803456,
                0.6860861323698916
              ],
              [
                0.5107913367420557,
                0.6849856757395781
              ],
              [
                0.5179487188669474,
                0.6840422413529466
              ],
              [
                0.5247202256379204,
                0.6823857729629843
              ],
              [
                0.53109272425626,
                0.6802461183056857
              ],
              [
                0.537761459522267,
                0.6791302891573271
              ],
              [
                0.5442822951760666,
                0.677271064695639
              ],
              [
                0.5510314560900008,
                0.6765472916100289
              ],
              [
                0.5576389748831828,
                0.6755838104307935
              ],
              [
                0.5644402341900977,
                0.6747570522155573
              ],
              [
                0.5708257237060994,
                0.6738748186757694
              ],
              [
                0.5771739588937644,
                0.6731029922312181
              ],
              [
                0.5835555088693514,
                0.672325673868863
              ],
              [
                0.589696484553591,
                0.6712007121112928
              ],
              [
                0.5954819147127413,
                0.6698776436056582
              ],
              [
                0.6015190810045784,
                0.6685922931874635
              ],
              [
                0.6073139468994693,
                0.6669366682194955
              ],
              [
                0.6125577936042366,
                0.6651279212058987
              ],
              [
                0.6175273292424596,
                0.6628477881812533
              ],
              [
                0.6228978181789262,
                0.661131844567901
              ],
              [
                0.6277221497455265,
                0.6591440748958558
              ],
              [
                0.6323662063070108,
                0.6569709121524119
              ],
              [
                0.6367819276486205,
                0.6548763769692258
              ],
              [
                0.6407579151670373,
                0.652588114406625
              ],
              [
                0.6443894167976704,
                0.6497494727474908
              ],
              [
                0.647871294902578,
                0.6468077304265566
              ],
              [
                0.6507999081843236,
                0.6431447271188881
              ],
              [
                0.652686454100181,
                0.6394538148990094
              ],
              [
                0.6541436842879835,
                0.6350760336552811
              ],
              [
                0.655340319086303,
                0.6298476188679558
              ]
            ],
            [
              Infinity,
              0.9553688764572144,
              0.9469184279441833,
              0.9430355429649353,
              0.9404308199882507,
              0.9374537467956543,
              0.9349238872528076,
              0.9325612783432007,
              0.9299717545509338,
              0.9275497794151306,
              0.9250184297561646,
              0.9223502278327942,
              0.9195886254310608,
              0.9164801836013794,
              0.913456916809082,
              0.9104994535446167,
              0.90753573179245,
              0.9047020077705383,
              0.901607096195221,
              0.8984284996986389,
              0.8950908184051514,
              0.8917452692985535,
              0.8883246183395386,
              0.8847042918205261,
              0.8809929490089417,
              0.8772799372673035,
              0.8733413219451904,
              0.8694285154342651,
              0.8655374646186829,
              0.8613735437393188,
              0.8573026657104492,
              0.8529676795005798,
              0.8486684560775757,
              0.8438785672187805,
              0.839259147644043,
              0.8345372080802917,
              0.8294042348861694,
              0.8237608075141907,
              0.8185992240905762,
              0.8131728172302246,
              0.8078856468200684,
              0.8018792867660522,
              0.796286940574646,
              0.7904803156852722,
              0.7841759324073792,
              0.7780383825302124,
              0.7716863751411438,
              0.7653847336769104,
              0.7590755224227905,
              0.7527335286140442,
              0.7463921308517456,
              0.7399284243583679,
              0.7332916259765625,
              0.7271493673324585,
              0.7205849885940552,
              0.7141554355621338,
              0.7074505686759949,
              0.7012734413146973,
              0.694890022277832,
              0.6886333227157593,
              0.6821579933166504,
              0.6753755807876587,
              0.669320821762085,
              0.6630825996398926,
              0.6565824747085571,
              0.6500669717788696,
              0.6438805460929871,
              0.6374486684799194,
              0.6308950185775757,
              0.6244288086891174,
              0.6179102659225464,
              0.6113512516021729,
              0.6051616668701172,
              0.5986646413803101,
              0.5921465158462524,
              0.5859599113464355,
              0.5796540975570679,
              0.573030412197113,
              0.566089391708374,
              0.5599501132965088,
              0.5533775687217712,
              0.5469143986701965,
              0.5403167605400085,
              0.5333980917930603,
              0.5267260074615479,
              0.5190610289573669,
              0.5112450122833252,
              0.5021182894706726,
              0.49257656931877136,
              0.4820423126220703,
              0.4698542654514313,
              0.4561774730682373,
              0.440491259098053,
              0.4228678047657013,
              0.40028879046440125,
              0.37107837200164795,
              0.33268460631370544,
              0.27929216623306274,
              0.20374177396297455,
              -Infinity
            ]
          ]
        ],
        [
          [
            [
              0.0,
              0.014720965068453419,
              0.03423270190597744,
              0.042333611166218525,
              0.049414688676346685,
              0.058142769552502326,
              0.06621230735651186,
              0.07549193801963473,
              0.08426415743516573,
              0.09423009768617374,
              0.10430467278489895,
              0.11490539330514156,
              0.12693481736493,
              0.1387464570508892,
              0.1502039607657182,
              0.1620344608254254,
              0.17442044432898654,
              0.18605805158547412,
              0.19799391656051746,
              0.20868815329871296,
              0.21997192191115283,
              0.23134668678865816,
              0.24134101688772674,
              0.2519631033620115,
              0.2628689777375853,
              0.27330998689135044,
              0.2833391070865476,
              0.29375460813021526,
              0.30339494101757264,
              0.3139136981191122,
              0.3240572516337747,
              0.3332519753898857,
              0.34238208354461,
              0.3509244632072244,
              0.359466465026959,
              0.3681476007738452,
              0.3768379626770336,
              0.385263510831455,
              0.39351598991375625,
              0.401309282642983,
              0.40894020600882125,
              0.41640776431661536,
              0.42411084469977167,
              0.4319776177855439,
              0.43909683258152793,
              0.4462372156641136,
              0.4535791532368032,
              0.4598494307822229,
              0.4663188750063073,
              0.47238368042755924,
              0.4786818301420226,
              0.4847971290118568,
              0.49120933052547494,
              0.4970822025155936,
              0.503143153743354,
              0.5087445566029846,
              0.5146062581028352,
              0.5195890563252199,
              0.5245010285076319,
              0.5295399087697017,
              0.5344778693295275,
              0.5402951625827853,
              0.5451514542254497,
              0.5501820261499799,
              0.555141024107498,
              0.5598142673946693,
              0.5641523647815817,
              0.568736297070503,
              0.5730811586275175,
              0.5769936565310414,
              0.5808580611829028,
              0.585200660839018,
              0.5895199120213316,
              0.5932562959280376,
              0.5964867160894956,
              0.6002343197729788,
              0.6035375312423453,
              0.6073725859267116,
              0.6109712989131756,
              0.6146882869291458,
              0.6180845399517775,
              0.6214583391620009,
              0.6248032953006769,
              0.6278143871027919,
              0.6304927626542374,
              0.6332846550889294,
              0.6357304214768598,
              0.6377613636214161,
              0.6393854718974252,
              0.6414455918860696,
              0.6430494914900069,
              0.6444337907036713,
              0.6457024124834424,
              0.6466189095393381,
              0.6470583446503226,
              0.6473390758113502,
              0.6469496730207825,
              0.6460023776374227,
              0.6444688530222233,
              0.6423411352299278
            ],
            [
              0.007416134872954056,
              0.9808452340391114
            ]
          ]
        ]
      ]
    }
  }
}